TransportPy/__init__.py
transplan-0.0.2.dist-info/LICENSE
transplan-0.0.2.dist-info/METADATA
transplan-0.0.2.dist-info/WHEEL
transplan-0.0.2.dist-info/dependency_links.txt
transplan-0.0.2.dist-info/top_level.txt
transplan-0.0.2.dist-info/RECORD
