Metadata-Version: 2.1
Name: transplan
Version: 0.0.2
Summary: Python parenting SATURN tools
Home-page: https://github.com/vjsequi/TransportPy
Author: Victor Sequi
Author-email: vjsequi@gmail.com
License: GNU General Public License v3.0
Platform: UNKNOWN
Classifier: Programming Language :: Python :: 3
Classifier: Operating System :: OS Independent
Requires-Python: >=3.7
